{
  "stockAdjustmentCreation.title": "${facilityCode}-${facilityName}-${program}",
  "stockAdjustmentCreation.keyword": "关键字",
  "stockAdjustmentCreation.search": "搜索",
  "stockAdjustmentCreation.product": "物品",
  "stockAdjustmentCreation.productWithDisplayUnit": "${fullProductName}-${displayUnit}",
  "stockAdjustmentCreation.reason": "原因",
  "stockAdjustmentCreation.reasonComments": "原因备注",
  "stockAdjustmentCreation.date": "日期",
  "stockAdjustmentCreation.add": "添加",
  "stockAdjustmentCreation.noProducts": "您尚未添加任何物品，请添加要调整的物品。",
  "stockAdjustmentCreation.productCode": "物品代码",
  "stockAdjustmentCreation.lotCode": "批次号",
  "stockAdjustmentCreation.expiryDate": "过期日期",
  "stockAdjustmentCreation.soh": "账面库存",
  "stockAdjustmentCreation.quantity": "数量",
  "stockAdjustmentCreation.actions": "操作",
  "stockAdjustmentCreation.remove": "删除",
  "stockAdjustmentCreation.clear": "清空",
  "stockAdjustmentCreation.clearAll": "您确定要清除吗？这将移除所有包和数量",
  "stockAdjustmentCreation.submit": "提交",
  "stockAdjustmentCreation.positiveInteger": "请输入正数",
  "stockAdjustmentCreation.sohCanNotBeNegative": "账面库存不能为负",
  "stockAdjustmentCreation.submitted": "调整已成功提交",
  "stockAdjustmentCreation.submitFailed": "调整提交失败",
  "stockAdjustmentCreation.submitInvalid": "调整里含无效字段",
  "stockAdjustmentCreation.confirmInfo": "${username}，您是否确认${number}笔调整？",
  "stockAdjustmentCreation.confirm": "确认",
  "stockAdjustmentCreation.selectStatus": "选择状态",
  "stockAdjustmentCreation.vvmStatus": "疫苗温度检测卡状态",
  "stockAdjustmentCreation.quantityGreaterThanStockOnHand": "调整的药品数量的数量不能大于手里的药品数"
}
